Workbook

Sheet Assumptions
A1: VESSEL — Packaging Assumptions (editable inputs)
A2: Blue = editable input. Everything else on this sheet and workbook is a formula. Unknown costs (printing, VAT, delivery) are left BLANK deliberately — a blank is not a confirmed zero. Change any blue cell and every other sheet recalculates.
A4: Assumption | B4: Value | C4: Notes
A5: Total Units to Sell | B5: 120 | C5: CONFIRMED — 8 SKUs x 15 units = 120.
A6: Bundle-Order % | B6: 0.15 | C6: MODEL ASSUMPTION — reproduces the financial model's existing 1.15 items/order and ~104-order figures (120 / 1.15 ~ 104.35). True bundle take rate is unknown; edit freely.
A7: Average Items per Order (= 1 + Bundle-Order %) | B7: =B6+1 -> 1.15 | C7: Derived. Normal order = 1 item, bundle order = 2 items.
A8: Expected Orders (calculated) | B8: =B5/B7 -> 104.34783 | C8: Formula: Total Units / Average Items per Order.
A9: Manual Order Count Override (optional) | C9: Leave BLANK to use the calculated figure above. If you override, check the Consistency Check row below.
A10: Orders Used | B10: =IF(ISBLANK(B9),B8,B9) -> 104.34783 | C10: Formula: Override if given, else the calculated figure.
A11: Consistency Check | B11: =IF(ABS(B10*B7-B5)<0.5,"OK","WARNING: Orders x Avg items per order does not equal Total Units - check the override") -> OK | C11: Only flags a problem when the manual override is used and is inconsistent with Total Units.
A12: Spare / Waste Buffer % | B12: 0.05 | C12: Editable buffer applied on top of calculated requirements (damage, re-packing, samples). Adjust based on real experience.
A13: USD -> ILS Rate | B13: 3.571 | C13: Sourced from the financial model: ~₪7,000 total supplier payment / US$1,960.10 invoice ~ ₪3.571/US$. Reused here for consistency, not a new rate.
A14: Pouch Unit Cost (US$) | B14: 0.28 | C14: CONFIRMED — supplier invoice, 10 Aug 2026 (500 pouches @ US$0.28 = US$140).
A15: Cloth Unit Cost (US$) | B15: 0.2 | C15: CONFIRMED — supplier invoice, 10 Aug 2026 (500 cloths @ US$0.20 = US$100).
A16: VAT Included in Component Quotes? | B16: Unknown | C16: OPEN ITEM — must be confirmed with each vendor. Do not assume Yes or No.
A17: VAT % (used only if quotes exclude VAT) | B17: 0.18 | C17: Editable. Standard Israeli VAT rate, for scenario testing.
A18: Vendor Delivery Cost (₪, flat) | C18: UNKNOWN — leave BLANK until quoted. A blank here means unresolved, not ₪0.
A19: Box Printing Cost per Unit (₪) | C19: UNKNOWN — leave BLANK until quoted. A blank here means unresolved, not ₪0.
A21: Derived (used by the Component Requirements sheet)
A22: Bundle Orders (count) | B22: =B10*B6 -> 15.652174
A23: Normal Orders (count) | B23: =B10*(1-B6) -> 88.695652
A24: Total Pouches Required (before waste) | B24: =B23*1+B22*2 -> 120
A25: Total Per-Order Components Required (before waste) — cloths/cards/stickers/boxes | B25: =B10 -> 104.34783
A27: Confirmed supplier-payment facts (whole invoice — no line-item allocation)
A28: Total Supplier Invoice Value (US$) | B28: 1960.1 | C28: CONFIRMED — full supplier order invoice total, 10 Aug 2026.
A29: Total Supplier Deposit Already Paid (₪, approximate) | B29: 3500 | C29: CONFIRMED — ~50% of the ~₪7,000 total committed supplier cost, for the WHOLE invoice. Not allocated to individual invoice lines — no per-line deposit split is a confirmed fact.
A30: Total Supplier Balance Remaining (₪, approximate) | B30: 3500 | C30: CONFIRMED — due before shipment, for the whole supplier invoice.

Sheet Component Requirements & Costs
A1: VESSEL — Packaging Component Requirements & Costs
A2: Vendors quote fixed lots, not a per-unit rate you can buy any quantity of. 'Economic Usage Cost' values what is actually consumed at the quoted rate, for planning only — it is NOT a real purchase option unless the required quantity happens to equal the quoted lot. 'Actual Cash Required' is what you would really pay: ₪0 if already covered by stock on order, the FULL lot price if the only quoted lot is adequate and nothing is on order yet, or UNKNOWN if the only quoted lot is too small and no covering quote exists.
A4: Component | B4: Required Qty (before waste) | C4: Required Qty incl. Waste Buffer | D4: Available Quoted Purchase Qty | E4: Available Quoted Purchase Price (₪) | F4: Quoted Unit Rate (₪) | G4: Economic Usage Cost at Quoted Rate (₪) — analytical only, NOT a purchase price | H4: Quote Adequate for Required Qty? | I4: Already Ordered Qty | J4: Already Received Qty | K4: Actual Cash Required for Available Purchase | L4: Surplus After Purchase | M4: Notes / Source
A5: Pouches (velvet, logo-embossed) | B5: =Assumptions!B24 -> 120 | C5: =ROUNDUP(B5*(1+Assumptions!B12),0) -> 126 | D5: 500 | E5: =D5*Assumptions!B14*Assumptions!B13 -> 499.94 | F5: =E5/D5 -> 0.99988 | G5: =C5*F5 -> 125.98488 | H5: =IF(D5>=C5,"Yes","NO - insufficient") -> Yes | I5: 500 | J5: 0 | K5: =IF(I5>=C5,0,IF(H5="Yes",E5,"UNKNOWN - no quote covers required quantity")) -> 0 | L5: =IF(I5>=C5,I5-C5,IF(H5="Yes",(I5+D5)-C5,"UNKNOWN")) -> 374 | M5: Part of the jewelry supplier's invoice (10 Aug 2026); ordered together with the jewelry, ~50% paid, in production. Not yet received — confirm and inspect on arrival.
A6: Cleaning Cloths (silver-polishing) | B6: =Assumptions!B25 -> 104.34783 | C6: =ROUNDUP(B6*(1+Assumptions!B12),0) -> 110 | D6: 500 | E6: =D6*Assumptions!B15*Assumptions!B13 -> 357.1 | F6: =E6/D6 -> 0.7142 | G6: =C6*F6 -> 78.562 | H6: =IF(D6>=C6,"Yes","NO - insufficient") -> Yes | I6: 500 | J6: 0 | K6: =IF(I6>=C6,0,IF(H6="Yes",E6,"UNKNOWN - no quote covers required quantity")) -> 0 | L6: =IF(I6>=C6,I6-C6,IF(H6="Yes",(I6+D6)-C6,"UNKNOWN")) -> 390 | M6: Part of the jewelry supplier's invoice (10 Aug 2026); ordered together with the jewelry, ~50% paid, in production. Not yet received — confirm and inspect on arrival.
A7: Thank-You Cards | B7: =Assumptions!B25 -> 104.34783 | C7: =ROUNDUP(B7*(1+Assumptions!B12),0) -> 110 | D7: 1000 | E7: 250 | F7: =E7/D7 -> 0.25 | G7: =C7*F7 -> 27.5 | H7: =IF(D7>=C7,"Yes","NO - insufficient") -> Yes | I7: 0 | J7: 0 | K7: =IF(I7>=C7,0,IF(H7="Yes",E7,"UNKNOWN - no quote covers required quantity")) -> 250 | L7: =IF(I7>=C7,I7-C7,IF(H7="Yes",(I7+D7)-C7,"UNKNOWN")) -> 890 | M7: Only quoted lot on record: 1,000 for ₪250. Not ordered, not paid, not received. You cannot buy just the ~110 needed at this rate — the full 1,000-card lot is the only known purchase option.
A8: Stickers | B8: =Assumptions!B25 -> 104.34783 | C8: =ROUNDUP(B8*(1+Assumptions!B12),0) -> 110 | D8: 100 | E8: 80 | F8: =E8/D8 -> 0.8 | G8: =C8*F8 -> 88 | H8: =IF(D8>=C8,"Yes","NO - insufficient") -> NO - insufficient | I8: 0 | J8: 0 | K8: =IF(I8>=C8,0,IF(H8="Yes",E8,"UNKNOWN - no quote covers required quantity")) -> UNKNOWN - no quote covers required quantity | L8: =IF(I8>=C8,I8-C8,IF(H8="Yes",(I8+D8)-C8,"UNKNOWN")) -> UNKNOWN | M8: Only quoted lot on record: 100 for ₪80 — INSUFFICIENT for the required quantity. No quote exists yet for a lot that actually covers what's needed. This row is the sticker-sufficiency check.
A9: Cardboard Shipping Boxes (unprinted) | B9: =Assumptions!B25 -> 104.34783 | C9: =ROUNDUP(B9*(1+Assumptions!B12),0) -> 110 | D9: 160 | E9: 700 | F9: =E9/D9 -> 4.375 | G9: =C9*F9 -> 481.25 | H9: =IF(D9>=C9,"Yes","NO - insufficient") -> Yes | I9: 0 | J9: 0 | K9: =IF(I9>=C9,0,IF(H9="Yes",E9,"UNKNOWN - no quote covers required quantity")) -> 700 | L9: =IF(I9>=C9,I9-C9,IF(H9="Yes",(I9+D9)-C9,"UNKNOWN")) -> 50 | M9: Only quoted lot on record: 160 unprinted for ₪700. Not ordered, not paid, not received. Printing cost is a separate line below. The full 160-box lot is the only known purchase option.
A10: Box Printing (add-on, per box) | B10: =B9 -> 104.34783 | C10: =C9 -> 110 | F10: =IF(ISBLANK(Assumptions!B19),"UNKNOWN",Assumptions!B19) -> UNKNOWN | G10: =IF(ISNUMBER(F10),C10*F10,"UNKNOWN") -> UNKNOWN | K10: =IF(ISNUMBER(F10),C10*F10,"UNKNOWN") -> UNKNOWN | M10: No fixed-lot quote exists for printing at all yet — cost has not been obtained from any vendor. Quantity mirrors the box requirement above; printing is priced per box, not a separately stocked item.

Sheet Summary
A1: VESSEL — Packaging Summary (auto-calculated)
A2: Every figure below is a formula reading 'Assumptions' and 'Component Requirements & Costs'. 'Cash required' figures reflect real, purchasable vendor lots — never a linear fraction of a bulk quote. Figures that depend on an unresolved input (an inadequate sticker quote, box printing, VAT status, vendor delivery) display UNKNOWN or INCOMPLETE - COST UNKNOWN rather than silently computing as zero.
A4: Full Program Economic Value (all required components valued at their quoted unit rate — an analytical value, NOT a purchase price; excludes printing) | F4: =SUM('Component Requirements & Costs'!G5:G9) -> 801.29688
A6: Supplier-order packaging value & deposit status (informational — not additive to cash-required figures below)
A7: Total Pouch/Cloth Value Included in Supplier Invoice | F7: ='Component Requirements & Costs'!E5+'Component Requirements & Costs'!E6 -> 857.04
A8: Total Supplier Deposit Already Paid (approximate, whole invoice) | F8: =Assumptions!B29 -> 3500
A9: Total Supplier Balance Remaining (approximate, whole invoice) | F9: =Assumptions!B30 -> 3500
A11: Additional cash required (new purchases only — pouches/cloths need none, see note above)
A12: Known quoted cash required (cards + boxes — full available lots, the only purchasable quantities at a known price) | F12: ='Component Requirements & Costs'!K7+'Component Requirements & Costs'!K9 -> 950
A13: Stickers (only quoted lot is insufficient — see Component sheet) | F13: ='Component Requirements & Costs'!K8 -> UNKNOWN - no quote covers required quantity
A14: Box printing add-on | F14: ='Component Requirements & Costs'!K10 -> UNKNOWN
A15: VAT adjustment (applied to the known quoted cash-required figure only) | F15: =IF(Assumptions!B16="Yes",0,IF(Assumptions!B16="No",F12*Assumptions!B17,"UNKNOWN")) -> UNKNOWN
A16: Vendor delivery (flat) | F16: =IF(ISBLANK(Assumptions!B18),"UNKNOWN",Assumptions!B18) -> UNKNOWN
A17: TOTAL ADDITIONAL CASH REQUIRED (all-in) | F17: =IF(AND(ISNUMBER(F13),ISNUMBER(F14),ISNUMBER(F15),ISNUMBER(F16)),F12+F13+F14+F15+F16,"INCOMPLETE - COST UNKNOWN") -> INCOMPLETE - COST UNKNOWN
A19: Packaging cost per order (economic allocation at quoted unit rate — NOT a claim about purchasable quantities)
A20: Per normal order (1 item: 1 pouch, 1 cloth, 1 card, 1 sticker, 1 box + printing) | F20: =IF(ISNUMBER('Component Requirements & Costs'!F10),'Component Requirements & Costs'!F5+'Component Requirements & Costs'!F6+'Component Requirements & Costs'!F7+'Component Requirements & Costs'!F8+'Component Requirements & Costs'!F9+'Component Requirements & Costs'!F10,"INCOMPLETE - COST UNKNOWN (printing not yet quoted)") -> INCOMPLETE - COST UNKNOWN (printing not yet quoted)
A21: Per bundle order (2 items: 2 pouches, 1 cloth, 1 card, 1 sticker, 1 box + printing) | F21: =IF(ISNUMBER('Component Requirements & Costs'!F10),'Component Requirements & Costs'!F5*2+'Component Requirements & Costs'!F6+'Component Requirements & Costs'!F7+'Component Requirements & Costs'!F8+'Component Requirements & Costs'!F9+'Component Requirements & Costs'!F10,"INCOMPLETE - COST UNKNOWN (printing not yet quoted)") -> INCOMPLETE - COST UNKNOWN (printing not yet quoted)
A23: Sticker sufficiency check
A24: Are the 100 quoted stickers enough? | F24: =IF('Component Requirements & Costs'!D8>='Component Requirements & Costs'!C8,"Sufficient - quote covers requirement","SHORTFALL - quoted 100 is NOT enough, 0 are currently ordered, and the price for an adequate quantity is unknown") -> SHORTFALL - quoted 100 is NOT enough, 0 are currently ordered, and the price for an adequate quantity is unknown
